sequntial_calibrationWithSA/VSA.py
sequntial_calibrationWithSA/__init__.py
sequntial_calibrationWithSA/ex.py
sequntial_calibrationWithSA-0.0.3.dist-info/METADATA
sequntial_calibrationWithSA-0.0.3.dist-info/WHEEL
sequntial_calibrationWithSA-0.0.3.dist-info/top_level.txt
sequntial_calibrationWithSA-0.0.3.dist-info/RECORD
